ChangeLog
LICENSE
MANIFEST.in
README.md
README.rst
setup.py
bin/rextract
rextract/VERSION
rextract/__init__.py
rextract/rextract.py
rextract.egg-info/PKG-INFO
rextract.egg-info/SOURCES.txt
rextract.egg-info/dependency_links.txt
rextract.egg-info/top_level.txt