Metadata-Version: 1.1
Name: rextract
Version: 1.1.0
Summary: Powerful commandline tool to extract and manipulate strings using regular exressions
Home-page: https://github.com/tranvietanh1991/rextract
Author: V.Anh Tran
Author-email: tranvietanh1991@gmail.com
License: GPLv3
Keywords: rextract,regex,extract,re,sed,grep,format,reformat,text,manipulate,strings,input,output,io,cli,commandline
Platform: UNKNOWN
Classifier: Development Status :: 5 - Production/Stable
Classifier: Environment :: Console
Classifier: Topic :: Text Processing
Classifier: Topic :: Text Processing :: General
Classifier: Topic :: Text Processing :: Filters
Classifier: Topic :: Utilities
Classifier: Programming Language :: Python
Classifier: License :: OSI Approved :: GNU General Public License v3 (GPLv3)
Classifier: Programming Language :: Python :: 2
Classifier: Programming Language :: Python :: 2
Classifier: Programming Language :: Python :: 2.7
Classifier: Programming Language :: Python :: 3
Classifier: Programming Language :: Python :: 3.4
Classifier: Programming Language :: Python :: 3.5
